{
  "config": {
    "configFile": "/Users/ndonga/Downloads/multibank-automation/playwright.config.ts",
    "rootDir": "/Users/ndonga/Downloads/multibank-automation/src/tests",
    "forbidOnly": false,
    "fullyParallel": false,
    "globalSetup": null,
    "globalTeardown": null,
    "globalTimeout": 0,
    "grep": {},
    "grepInvert": null,
    "maxFailures": 0,
    "metadata": {
      "actualWorkers": 1
    },
    "preserveOutput": "always",
    "projects": [
      {
        "outputDir": "/Users/ndonga/Downloads/multibank-automation/reports/artifacts",
        "repeatEach": 1,
        "retries": 1,
        "metadata": {
          "actualWorkers": 1
        },
        "id": "chromium",
        "name": "chromium",
        "testDir": "/Users/ndonga/Downloads/multibank-automation/src/tests",
        "testIgnore": [],
        "testMatch": [
          "**/*.@(spec|test).?(c|m)[jt]s?(x)"
        ],
        "timeout": 30000
      }
    ],
    "quiet": false,
    "reporter": [
      [
        "html",
        {
          "outputFolder": "reports/html",
          "open": "never"
        }
      ],
      [
        "json",
        {
          "outputFile": "reports/results.json"
        }
      ],
      [
        "list",
        null
      ]
    ],
    "reportSlowTests": {
      "max": 5,
      "threshold": 300000
    },
    "runAgents": "none",
    "shard": null,
    "tags": [],
    "updateSnapshots": "missing",
    "updateSourceMethod": "patch",
    "version": "1.58.2",
    "workers": 1,
    "webServer": null
  },
  "suites": [
    {
      "title": "navigation.spec.ts",
      "file": "navigation.spec.ts",
      "column": 0,
      "line": 0,
      "specs": [],
      "suites": [
        {
          "title": "Navigation & Layout @navigation",
          "file": "navigation.spec.ts",
          "line": 14,
          "column": 6,
          "specs": [
            {
              "title": "header is visible on page load",
              "ok": true,
              "tags": [
                "navigation"
              ],
              "tests": [
                {
                  "timeout": 30000,
                  "annotations": [],
                  "expectedStatus": "passed",
                  "projectId": "chromium",
                  "projectName": "chromium",
                  "results": [
                    {
                      "workerIndex": 0,
                      "parallelIndex": 0,
                      "status": "passed",
                      "duration": 3330,
                      "errors": [],
                      "stdout": [],
                      "stderr": [],
                      "retry": 0,
                      "startTime": "2026-03-01T07:26:12.805Z",
                      "annotations": [],
                      "attachments": []
                    }
                  ],
                  "status": "expected"
                }
              ],
              "id": "5d2868f7d23420c27cca-c9bd52de6a61155eade9",
              "file": "navigation.spec.ts",
              "line": 22,
              "column": 7
            },
            {
              "title": "main navigation is visible on desktop",
              "ok": true,
              "tags": [
                "navigation"
              ],
              "tests": [
                {
                  "timeout": 30000,
                  "annotations": [],
                  "expectedStatus": "passed",
                  "projectId": "chromium",
                  "projectName": "chromium",
                  "results": [
                    {
                      "workerIndex": 0,
                      "parallelIndex": 0,
                      "status": "passed",
                      "duration": 3681,
                      "errors": [],
                      "stdout": [],
                      "stderr": [],
                      "retry": 0,
                      "startTime": "2026-03-01T07:26:16.898Z",
                      "annotations": [],
                      "attachments": []
                    }
                  ],
                  "status": "expected"
                }
              ],
              "id": "5d2868f7d23420c27cca-ce43d583f0d2ada32fbc",
              "file": "navigation.spec.ts",
              "line": 26,
              "column": 7
            },
            {
              "title": "navigation contains exactly the expected number of links",
              "ok": true,
              "tags": [
                "navigation"
              ],
              "tests": [
                {
                  "timeout": 30000,
                  "annotations": [],
                  "expectedStatus": "passed",
                  "projectId": "chromium",
                  "projectName": "chromium",
                  "results": [
                    {
                      "workerIndex": 0,
                      "parallelIndex": 0,
                      "status": "passed",
                      "duration": 2676,
                      "errors": [],
                      "stdout": [],
                      "stderr": [],
                      "retry": 0,
                      "startTime": "2026-03-01T07:26:20.589Z",
                      "annotations": [],
                      "attachments": []
                    }
                  ],
                  "status": "expected"
                }
              ],
              "id": "5d2868f7d23420c27cca-9afcfff07fca9333feaf",
              "file": "navigation.spec.ts",
              "line": 30,
              "column": 7
            },
            {
              "title": "all expected nav items are present",
              "ok": true,
              "tags": [
                "navigation"
              ],
              "tests": [
                {
                  "timeout": 30000,
                  "annotations": [],
                  "expectedStatus": "passed",
                  "projectId": "chromium",
                  "projectName": "chromium",
                  "results": [
                    {
                      "workerIndex": 0,
                      "parallelIndex": 0,
                      "status": "passed",
                      "duration": 3081,
                      "errors": [],
                      "stdout": [],
                      "stderr": [],
                      "retry": 0,
                      "startTime": "2026-03-01T07:26:23.270Z",
                      "annotations": [],
                      "attachments": []
                    }
                  ],
                  "status": "expected"
                }
              ],
              "id": "5d2868f7d23420c27cca-bf300635edd9d63356e0",
              "file": "navigation.spec.ts",
              "line": 35,
              "column": 7
            },
            {
              "title": "each nav link is visible and not hidden",
              "ok": true,
              "tags": [
                "navigation"
              ],
              "tests": [
                {
                  "timeout": 30000,
                  "annotations": [],
                  "expectedStatus": "passed",
                  "projectId": "chromium",
                  "projectName": "chromium",
                  "results": [
                    {
                      "workerIndex": 0,
                      "parallelIndex": 0,
                      "status": "passed",
                      "duration": 2815,
                      "errors": [],
                      "stdout": [],
                      "stderr": [],
                      "retry": 0,
                      "startTime": "2026-03-01T07:26:26.356Z",
                      "annotations": [],
                      "attachments": []
                    }
                  ],
                  "status": "expected"
                }
              ],
              "id": "5d2868f7d23420c27cca-381aea97a7ad48bb6456",
              "file": "navigation.spec.ts",
              "line": 48,
              "column": 7
            },
            {
              "title": "Sign in and Sign up buttons are visible in header",
              "ok": true,
              "tags": [
                "navigation"
              ],
              "tests": [
                {
                  "timeout": 30000,
                  "annotations": [],
                  "expectedStatus": "passed",
                  "projectId": "chromium",
                  "projectName": "chromium",
                  "results": [
                    {
                      "workerIndex": 0,
                      "parallelIndex": 0,
                      "status": "passed",
                      "duration": 2472,
                      "errors": [],
                      "stdout": [],
                      "stderr": [],
                      "retry": 0,
                      "startTime": "2026-03-01T07:26:29.176Z",
                      "annotations": [],
                      "attachments": []
                    }
                  ],
                  "status": "expected"
                }
              ],
              "id": "5d2868f7d23420c27cca-bc7e7b7756bc26b00a09",
              "file": "navigation.spec.ts",
              "line": 56,
              "column": 7
            },
            {
              "title": "Explore nav link points to /en/explore",
              "ok": true,
              "tags": [
                "navigation"
              ],
              "tests": [
                {
                  "timeout": 30000,
                  "annotations": [],
                  "expectedStatus": "passed",
                  "projectId": "chromium",
                  "projectName": "chromium",
                  "results": [
                    {
                      "workerIndex": 0,
                      "parallelIndex": 0,
                      "status": "passed",
                      "duration": 2731,
                      "errors": [],
                      "stdout": [],
                      "stderr": [],
                      "retry": 0,
                      "startTime": "2026-03-01T07:26:31.654Z",
                      "annotations": [],
                      "attachments": []
                    }
                  ],
                  "status": "expected"
                }
              ],
              "id": "5d2868f7d23420c27cca-f7f32b3a8d9f31a64ef1",
              "file": "navigation.spec.ts",
              "line": 62,
              "column": 7
            },
            {
              "title": "Features nav link points to /en/features",
              "ok": true,
              "tags": [
                "navigation"
              ],
              "tests": [
                {
                  "timeout": 30000,
                  "annotations": [],
                  "expectedStatus": "passed",
                  "projectId": "chromium",
                  "projectName": "chromium",
                  "results": [
                    {
                      "workerIndex": 0,
                      "parallelIndex": 0,
                      "status": "passed",
                      "duration": 2377,
                      "errors": [],
                      "stdout": [],
                      "stderr": [],
                      "retry": 0,
                      "startTime": "2026-03-01T07:26:34.393Z",
                      "annotations": [],
                      "attachments": []
                    }
                  ],
                  "status": "expected"
                }
              ],
              "id": "5d2868f7d23420c27cca-4f7727accd3a7ad3cd72",
              "file": "navigation.spec.ts",
              "line": 67,
              "column": 7
            },
            {
              "title": "Company nav link points to /en/company",
              "ok": true,
              "tags": [
                "navigation"
              ],
              "tests": [
                {
                  "timeout": 30000,
                  "annotations": [],
                  "expectedStatus": "passed",
                  "projectId": "chromium",
                  "projectName": "chromium",
                  "results": [
                    {
                      "workerIndex": 0,
                      "parallelIndex": 0,
                      "status": "passed",
                      "duration": 2666,
                      "errors": [],
                      "stdout": [],
                      "stderr": [],
                      "retry": 0,
                      "startTime": "2026-03-01T07:26:36.776Z",
                      "annotations": [],
                      "attachments": []
                    }
                  ],
                  "status": "expected"
                }
              ],
              "id": "5d2868f7d23420c27cca-346c72e862df497571b1",
              "file": "navigation.spec.ts",
              "line": 72,
              "column": 7
            },
            {
              "title": "$MBG link is external and points to multibankgroup.com",
              "ok": true,
              "tags": [
                "navigation"
              ],
              "tests": [
                {
                  "timeout": 30000,
                  "annotations": [],
                  "expectedStatus": "passed",
                  "projectId": "chromium",
                  "projectName": "chromium",
                  "results": [
                    {
                      "workerIndex": 0,
                      "parallelIndex": 0,
                      "status": "passed",
                      "duration": 2675,
                      "errors": [],
                      "stdout": [],
                      "stderr": [],
                      "retry": 0,
                      "startTime": "2026-03-01T07:26:39.448Z",
                      "annotations": [],
                      "attachments": []
                    }
                  ],
                  "status": "expected"
                }
              ],
              "id": "5d2868f7d23420c27cca-05047936bb06fb11268a",
              "file": "navigation.spec.ts",
              "line": 77,
              "column": 7
            },
            {
              "title": "Sign in button links to trade.mb.io/login",
              "ok": true,
              "tags": [
                "navigation"
              ],
              "tests": [
                {
                  "timeout": 30000,
                  "annotations": [],
                  "expectedStatus": "passed",
                  "projectId": "chromium",
                  "projectName": "chromium",
                  "results": [
                    {
                      "workerIndex": 0,
                      "parallelIndex": 0,
                      "status": "passed",
                      "duration": 2480,
                      "errors": [],
                      "stdout": [],
                      "stderr": [],
                      "retry": 0,
                      "startTime": "2026-03-01T07:26:42.128Z",
                      "annotations": [],
                      "attachments": []
                    }
                  ],
                  "status": "expected"
                }
              ],
              "id": "5d2868f7d23420c27cca-8316d5e64adb67c0a9c6",
              "file": "navigation.spec.ts",
              "line": 82,
              "column": 7
            },
            {
              "title": "Sign up button links to trade.mb.io/register",
              "ok": true,
              "tags": [
                "navigation"
              ],
              "tests": [
                {
                  "timeout": 30000,
                  "annotations": [],
                  "expectedStatus": "passed",
                  "projectId": "chromium",
                  "projectName": "chromium",
                  "results": [
                    {
                      "workerIndex": 0,
                      "parallelIndex": 0,
                      "status": "passed",
                      "duration": 2603,
                      "errors": [],
                      "stdout": [],
                      "stderr": [],
                      "retry": 0,
                      "startTime": "2026-03-01T07:26:44.614Z",
                      "annotations": [],
                      "attachments": []
                    }
                  ],
                  "status": "expected"
                }
              ],
              "id": "5d2868f7d23420c27cca-8506a71e366ea9beb4ca",
              "file": "navigation.spec.ts",
              "line": 87,
              "column": 7
            },
            {
              "title": "clicking Explore navigates to the Explore page",
              "ok": true,
              "tags": [
                "navigation"
              ],
              "tests": [
                {
                  "timeout": 30000,
                  "annotations": [],
                  "expectedStatus": "passed",
                  "projectId": "chromium",
                  "projectName": "chromium",
                  "results": [
                    {
                      "workerIndex": 0,
                      "parallelIndex": 0,
                      "status": "passed",
                      "duration": 2664,
                      "errors": [],
                      "stdout": [],
                      "stderr": [],
                      "retry": 0,
                      "startTime": "2026-03-01T07:26:47.222Z",
                      "annotations": [],
                      "attachments": []
                    }
                  ],
                  "status": "expected"
                }
              ],
              "id": "5d2868f7d23420c27cca-1ffb59336bf4c36b72f9",
              "file": "navigation.spec.ts",
              "line": 92,
              "column": 7
            },
            {
              "title": "clicking Features navigates to the Features page",
              "ok": true,
              "tags": [
                "navigation"
              ],
              "tests": [
                {
                  "timeout": 30000,
                  "annotations": [],
                  "expectedStatus": "passed",
                  "projectId": "chromium",
                  "projectName": "chromium",
                  "results": [
                    {
                      "workerIndex": 0,
                      "parallelIndex": 0,
                      "status": "passed",
                      "duration": 2383,
                      "errors": [],
                      "stdout": [],
                      "stderr": [],
                      "retry": 0,
                      "startTime": "2026-03-01T07:26:49.890Z",
                      "annotations": [],
                      "attachments": []
                    }
                  ],
                  "status": "expected"
                }
              ],
              "id": "5d2868f7d23420c27cca-6b8939c71b38f8e4f7fd",
              "file": "navigation.spec.ts",
              "line": 97,
              "column": 7
            },
            {
              "title": "clicking Company navigates to the Company page",
              "ok": true,
              "tags": [
                "navigation"
              ],
              "tests": [
                {
                  "timeout": 30000,
                  "annotations": [],
                  "expectedStatus": "passed",
                  "projectId": "chromium",
                  "projectName": "chromium",
                  "results": [
                    {
                      "workerIndex": 0,
                      "parallelIndex": 0,
                      "status": "passed",
                      "duration": 3012,
                      "errors": [],
                      "stdout": [],
                      "stderr": [],
                      "retry": 0,
                      "startTime": "2026-03-01T07:26:52.280Z",
                      "annotations": [],
                      "attachments": []
                    }
                  ],
                  "status": "expected"
                }
              ],
              "id": "5d2868f7d23420c27cca-829c5fe1e55fab11609f",
              "file": "navigation.spec.ts",
              "line": 102,
              "column": 7
            },
            {
              "title": "hero heading contains \"Crypto\"",
              "ok": true,
              "tags": [
                "navigation"
              ],
              "tests": [
                {
                  "timeout": 30000,
                  "annotations": [],
                  "expectedStatus": "passed",
                  "projectId": "chromium",
                  "projectName": "chromium",
                  "results": [
                    {
                      "workerIndex": 0,
                      "parallelIndex": 0,
                      "status": "passed",
                      "duration": 2576,
                      "errors": [],
                      "stdout": [],
                      "stderr": [],
                      "retry": 0,
                      "startTime": "2026-03-01T07:26:55.298Z",
                      "annotations": [],
                      "attachments": []
                    }
                  ],
                  "status": "expected"
                }
              ],
              "id": "5d2868f7d23420c27cca-1fc4ebd6ec5d88b2987e",
              "file": "navigation.spec.ts",
              "line": 107,
              "column": 7
            },
            {
              "title": "\"Download the app\" button is visible on hero",
              "ok": true,
              "tags": [
                "navigation"
              ],
              "tests": [
                {
                  "timeout": 30000,
                  "annotations": [],
                  "expectedStatus": "passed",
                  "projectId": "chromium",
                  "projectName": "chromium",
                  "results": [
                    {
                      "workerIndex": 0,
                      "parallelIndex": 0,
                      "status": "passed",
                      "duration": 2630,
                      "errors": [],
                      "stdout": [],
                      "stderr": [],
                      "retry": 0,
                      "startTime": "2026-03-01T07:26:57.878Z",
                      "annotations": [],
                      "attachments": []
                    }
                  ],
                  "status": "expected"
                }
              ],
              "id": "5d2868f7d23420c27cca-200a69d19efa5c61a004",
              "file": "navigation.spec.ts",
              "line": 112,
              "column": 7
            },
            {
              "title": "\"Open an account\" button is visible on hero",
              "ok": true,
              "tags": [
                "navigation"
              ],
              "tests": [
                {
                  "timeout": 30000,
                  "annotations": [],
                  "expectedStatus": "passed",
                  "projectId": "chromium",
                  "projectName": "chromium",
                  "results": [
                    {
                      "workerIndex": 0,
                      "parallelIndex": 0,
                      "status": "passed",
                      "duration": 2553,
                      "errors": [],
                      "stdout": [],
                      "stderr": [],
                      "retry": 0,
                      "startTime": "2026-03-01T07:27:00.513Z",
                      "annotations": [],
                      "attachments": []
                    }
                  ],
                  "status": "expected"
                }
              ],
              "id": "5d2868f7d23420c27cca-9e461f7a39a0676a97a4",
              "file": "navigation.spec.ts",
              "line": 116,
              "column": 7
            }
          ]
        }
      ]
    }
  ],
  "errors": [],
  "stats": {
    "startTime": "2026-03-01T07:26:12.269Z",
    "duration": 50896.69,
    "expected": 18,
    "skipped": 0,
    "unexpected": 0,
    "flaky": 0
  }
}